paymaxis/__init__.py
paymaxis/_base_client.py
paymaxis/_client.py
paymaxis/_compat.py
paymaxis/_constants.py
paymaxis/_exceptions.py
paymaxis/_files.py
paymaxis/_models.py
paymaxis/_qs.py
paymaxis/_resource.py
paymaxis/_response.py
paymaxis/_streaming.py
paymaxis/_types.py
paymaxis/_version.py
paymaxis/py.typed
paymaxis/_utils/__init__.py
paymaxis/_utils/_logs.py
paymaxis/_utils/_proxy.py
paymaxis/_utils/_reflection.py
paymaxis/_utils/_streams.py
paymaxis/_utils/_sync.py
paymaxis/_utils/_transform.py
paymaxis/_utils/_typing.py
paymaxis/_utils/_utils.py
paymaxis/lib/.keep
paymaxis/resources/__init__.py
paymaxis/resources/subscriptions.py
paymaxis/resources/payments/__init__.py
paymaxis/resources/payments/operations.py
paymaxis/resources/payments/payments.py
paymaxis/types/__init__.py
paymaxis/types/payment.py
paymaxis/types/payment_create_params.py
paymaxis/types/payment_list_params.py
paymaxis/types/payment_list_response.py
paymaxis/types/subscription.py
paymaxis/types/subscription_update_params.py
paymaxis/types/payments/__init__.py
paymaxis/types/payments/operation.py
paymaxis-0.1.0a3.dist-info/METADATA
paymaxis-0.1.0a3.dist-info/WHEEL
paymaxis-0.1.0a3.dist-info/licenses/LICENSE
paymaxis-0.1.0a3.dist-info/RECORD
